<?xml version="1.0" encoding="UTF-8"?>
<objects serializationModel="Studio.02.02.00">
	<object class="AudioFile" id="{bef0b453-9a85-49b1-8a5b-f82045a55928}">
		<property name="assetPath">
			<value>Ambience/birds/amb_bird_call_01.ogg</value>
		</property>
		<property name="frequencyInKHz">
			<value>48</value>
		</property>
		<property name="channelCount">
			<value>1</value>
		</property>
		<property name="length">
			<value>3</value>
		</property>
		<relationship name="masterAssetFolder">
			<destination>{9e82f377-26a1-4ed6-b466-c356839d120a}</destination>
		</relationship>
	</object>
</objects>
